python_step_parser/__init__.py
python_step_parser/child_type_register.py
python_step_parser/step_parser.py
python_step_parser/parsers/__init__.py
python_step_parser/parsers/cache_logic.py
python_step_parser/parsers/complex_item_dto.py
python_step_parser/parsers/complex_type_parsers.py
python_step_parser/parsers/db_helpers.py
python_step_parser/parsers/helpers.py
python_step_parser/parsers/parser.py
python_step_parser/step_types/__init__.py
python_step_parser/step_types/abstract_types.py
python_step_parser/step_types/advanced_brep_shape_representation.py
python_step_parser/step_types/advanced_face.py
python_step_parser/step_types/application_context.py
python_step_parser/step_types/application_context_element.py
python_step_parser/step_types/assembly_component_usage.py
python_step_parser/step_types/axis2_placement3d.py
python_step_parser/step_types/b_spline_curve.py
python_step_parser/step_types/b_spline_curve_with_knots.py
python_step_parser/step_types/b_spline_surface.py
python_step_parser/step_types/b_spline_surface_with_knots.py
python_step_parser/step_types/bounded_curve.py
python_step_parser/step_types/bounded_surface.py
python_step_parser/step_types/cartesian_point.py
python_step_parser/step_types/circle.py
python_step_parser/step_types/closed_shell.py
python_step_parser/step_types/colour_rgb.py
python_step_parser/step_types/conic.py
python_step_parser/step_types/conical_surface.py
python_step_parser/step_types/context_dependent_shape_representation.py
python_step_parser/step_types/curve.py
python_step_parser/step_types/cylindrical_surface.py
python_step_parser/step_types/degenerate_toroidal_surface.py
python_step_parser/step_types/derived_unit.py
python_step_parser/step_types/derived_unit_element.py
python_step_parser/step_types/direction.py
python_step_parser/step_types/draughting_pre_defined_colour.py
python_step_parser/step_types/edge.py
python_step_parser/step_types/edge_curve.py
python_step_parser/step_types/edge_loop.py
python_step_parser-0.2.3.dist-info/METADATA
python_step_parser-0.2.3.dist-info/WHEEL
python_step_parser-0.2.3.dist-info/licenses/LICENSE
python_step_parser-0.2.3.dist-info/RECORD
