Metadata-Version: 2.4
Name: python_step_parser
Version: 0.2.3
Summary: A library to extract and access data from a STEP or STP file in a structured way.
Project-URL: Homepage, https://github.com/andreabrake/python-step-parser
Project-URL: Issues, https://github.com/andreabrake/python-step-parser/issues
Author-email: Andrea Brake <andreadoescode@gmail.com>
License-Expression: MIT
License-File: LICENSE
Classifier: Operating System :: OS Independent
Classifier: Programming Language :: Python :: 3
Requires-Python: >=3.9
